libpy_gf_partition.dylib
libpy_gf_screening.dylib
libpy_config.dylib
libpy_gf_solver.dylib
libpy_gf_engine.dylib
libpy_gf_types.dylib
libpy_gf_utils.dylib
libpy_gf_io.dylib
libpy_const.dylib
libpy_gf_exceptions.dylib
libpy_gf_expectations.dylib
gridfire.cpython-310-darwin.so
libpy_composition.dylib
libpy_gf_reaction.dylib
fourdst.cpython-310-darwin.so
gridfire-0.5.0.data/headers/fourdst/fourdst/config/config.h
gridfire-0.5.0.data/headers/fourdst/fourdst/constants/const.h
gridfire-0.5.0.data/headers/fourdst/fourdst/composition/atomicSpecies.h
gridfire-0.5.0.data/headers/fourdst/fourdst/composition/composition.h
gridfire-0.5.0.data/headers/fourdst/fourdst/composition/species.h
gridfire-0.5.0.data/headers/fourdst/fourdst/logging/logging.h
gridfire-0.5.0.data/headers/eigen3/signature_of_eigen3_matrix_library
gridfire-0.5.0.data/headers/eigen3/unsupported/Eigen/MatrixFunctions
gridfire-0.5.0.data/headers/eigen3/unsupported/Eigen/AdolcForward
gridfire-0.5.0.data/headers/eigen3/unsupported/Eigen/AlignedVector3
gridfire-0.5.0.data/headers/eigen3/unsupported/Eigen/OpenGLSupport
gridfire-0.5.0.data/headers/eigen3/unsupported/Eigen/LevenbergMarquardt
gridfire-0.5.0.data/headers/eigen3/unsupported/Eigen/AutoDiff
gridfire-0.5.0.data/headers/eigen3/unsupported/Eigen/NumericalDiff
gridfire-0.5.0.data/headers/eigen3/unsupported/Eigen/NonLinearOptimization
gridfire-0.5.0.data/headers/eigen3/unsupported/Eigen/ArpackSupport
gridfire-0.5.0.data/headers/eigen3/unsupported/Eigen/Skyline
gridfire-0.5.0.data/headers/eigen3/unsupported/Eigen/BVH
gridfire-0.5.0.data/headers/eigen3/unsupported/Eigen/SpecialFunctions
gridfire-0.5.0.data/headers/eigen3/unsupported/Eigen/Splines
gridfire-0.5.0.data/headers/eigen3/unsupported/Eigen/KroneckerProduct
gridfire-0.5.0.data/headers/eigen3/unsupported/Eigen/IterativeSolvers
gridfire-0.5.0.data/headers/eigen3/unsupported/Eigen/FFT
gridfire-0.5.0.data/headers/eigen3/unsupported/Eigen/EulerAngles
gridfire-0.5.0.dist-info/RECORD
gridfire-0.5.0.dist-info/WHEEL
gridfire-0.5.0.dist-info/LICENSE.txt
gridfire-0.5.0.dist-info/METADATA
