Metadata-Version: 2.1
Name: gridfire
Version: 0.5.0
Summary: Python interface to the GridFire nuclear network code
Author-Email: "Emily M. Boudreaux" <emily@boudreauxmail.com>, Aaron Dotter <aaron.dotter@gmail.com>
Maintainer-Email: "Emily M. Boudreaux" <emily@boudreauxmail.com>
License:                     GNU GENERAL PUBLIC LICENSE
